sangheeMODEL/__init__.py
sangheeMODEL/classification/__init__.py
sangheeMODEL/classification/model.py
sangheeMODEL/mrc/__init__.py
sangheeMODEL/mrc/model.py
sangheeMODEL/ner/__init__.py
sangheeMODEL/ner/model.py
sangheeMODEL/summary/__init__.py
sangheeMODEL/summary/model.py
sangheeMODEL-0.0.0.dist-info/METADATA
sangheeMODEL-0.0.0.dist-info/WHEEL
sangheeMODEL-0.0.0.dist-info/top_level.txt
sangheeMODEL-0.0.0.dist-info/RECORD
