Metadata-Version: 2.1
Name: sangheeMODEL
Version: 0.0.0
Summary: sanghee's NLP models.
Home-page: https://github.com/ajskdlf64/sanghee-nlp-tool
Author: sanghee park
Author-email: parksangheeeee@naver.com
License: MIT
Classifier: Programming Language :: Python :: 3
Classifier: License :: OSI Approved :: MIT License
Classifier: Operating System :: OS Independent
